codescribe_ai/__init__.py
codescribe_ai/cli.py
codescribe_ai/main.py
codescribe_ai/api/__init__.py
codescribe_ai/api/main.py
codescribe_ai/api/routes.py
codescribe_ai/ci_cd/__init__.py
codescribe_ai/ci_cd/github_actions.py
codescribe_ai/ci_cd/webhook_handler.py
codescribe_ai/config/__init__.py
codescribe_ai/core/__init__.py
codescribe_ai/core/call_graph.py
codescribe_ai/core/dependency_parser.py
codescribe_ai/core/doc_generator.py
codescribe_ai/core/env_var_descriptions.py
codescribe_ai/core/env_var_parser.py
codescribe_ai/core/environment_config.py
codescribe_ai/core/formatter.py
codescribe_ai/core/import_graph.py
codescribe_ai/core/lang_detector.py
codescribe_ai/core/parser.py
codescribe_ai/core/project_summary.py
codescribe_ai/core/prompt_builder.py
codescribe_ai/core/repo_context.py
codescribe_ai/core/repo_downloader.py
codescribe_ai/core/summarizer.py
codescribe_ai/core/token_manager.py
codescribe_ai/core/tokenizer.py
codescribe_ai/core/usage_instruction_builder.py
codescribe_ai/scripts/__init__.py
codescribe_ai/scripts/run_pipeline.py
codescribe_ai/templates/prompt_templates.md
codescribe_ai/templates/readme_template.md
codescribe_ai/utils/__init__.py
codescribe_ai/utils/file_io.py
codescribe_ai/utils/logger.py
codescribe_ai/utils/token_utils.py
codescribe_ai-0.1.7.dist-info/METADATA
codescribe_ai-0.1.7.dist-info/WHEEL
codescribe_ai-0.1.7.dist-info/entry_points.txt
codescribe_ai-0.1.7.dist-info/top_level.txt
codescribe_ai-0.1.7.dist-info/RECORD
