Metadata-Version: 2.4
Name: codescribe-ai
Version: 0.1.7
Summary: AI-powered README generator for any codebase
Home-page: https://github.com/Mahi1609/codescribe_ai
Author: Mahesh Yannawar
Author-email: glory@gloryofm.online
Classifier: Programming Language :: Python :: 3
Classifier: License :: OSI Approved :: MIT License
Classifier: Operating System :: OS Independent
Requires-Python: >=3.8
Requires-Dist: flask
Requires-Dist: requests
Requires-Dist: jinja2
Requires-Dist: python-dotenv
Requires-Dist: click
Requires-Dist: pygments
Requires-Dist: gitpython
Requires-Dist: markdown
Requires-Dist: gunicorn
Requires-Dist: pytest
Dynamic: author
Dynamic: author-email
Dynamic: classifier
Dynamic: description-content-type
Dynamic: home-page
Dynamic: requires-dist
Dynamic: requires-python
Dynamic: summary
